wry_bokeh_helper-0.4.1.dist-info/METADATA
wry_bokeh_helper-0.4.1.dist-info/WHEEL
wry_bokeh_helper-0.4.1.dist-info/licenses/LICENSE
wry_bokeh_helper/bokeh_io.py
wry_bokeh_helper/py.typed
wry_bokeh_helper/_wry_bokeh_helper.py
wry_bokeh_helper/_wry_bokeh_helper.pyi
wry_bokeh_helper/__init__.py
wry_bokeh_helper/wry_bokeh_helper.cp310-win_amd64.pyd
wry_bokeh_helper-0.4.1.dist-info/RECORD
