Metadata-Version: 2.4
Name: wry_bokeh_helper
Version: 0.4.1
Classifier: Programming Language :: Rust
Classifier: Programming Language :: Python :: Implementation :: CPython
Classifier: Programming Language :: Python :: Implementation :: PyPy
Requires-Dist: pillow
Requires-Dist: pytest ; extra == 'tests'
Requires-Dist: ruff ; extra == 'dev'
Requires-Dist: bokeh ; extra == 'dev'
Provides-Extra: tests
Provides-Extra: dev
License-File: LICENSE
Requires-Python: >=3.8
